{
  "USDJPY": {
    "pair": "USDJPY",
    "entry_time": "2026-07-02T16:56:07.658113+00:00",
    "entry_date": "2026-07-02",
    "entry_price": 161.584,
    "direction": "LONG",
    "initial_stars": 5,
    "sl": 162.446,
    "initial_sl": 160.648,
    "tp": 162.052,
    "trail_distance": 0.624,
    "trail_atr_mult": 2.0,
    "be_target_after_tp": 162.052,
    "max_target": 163.456,
    "tp_mode": "single_with_trail",
    "tp_hit": true,
    "trail_active": true,
    "extreme_price": 163.07,
    "tp1": 162.052,
    "tp2": 162.988,
    "tp3": 163.456,
    "ta_score": 91.7,
    "fa_score": 76.6,
    "fa_rate_diff": 2.75,
    "regime": "normal",
    "current_price": 163.07,
    "current_stars": 4,
    "tp_hit_time": "2026-07-17T06:20:57.632116+00:00"
  },
  "KRWJPY": {
    "pair": "KRWJPY",
    "entry_time": "2026-07-21T14:09:41.994172+00:00",
    "entry_date": "2026-07-21",
    "entry_price": 0.11,
    "direction": "LONG",
    "initial_stars": 5,
    "sl": null,
    "initial_sl": null,
    "tp": null,
    "trail_distance": 0,
    "trail_atr_mult": 3.0,
    "be_target_after_tp": 0.11,
    "max_target": null,
    "tp_mode": "single_with_trail",
    "tp_hit": false,
    "trail_active": false,
    "extreme_price": 0.11,
    "tp1": null,
    "tp2": null,
    "tp3": null,
    "ta_score": 80.3,
    "fa_score": 82.1,
    "fa_rate_diff": 1.75,
    "regime": "normal",
    "current_price": 0.11016,
    "current_stars": 2
  },
  "GBPJPY": {
    "pair": "GBPJPY",
    "entry_time": "2026-07-22T16:25:34.978178+00:00",
    "entry_date": "2026-07-22",
    "entry_price": 217.987,
    "direction": "LONG",
    "initial_stars": 5,
    "sl": 217.664,
    "initial_sl": 217.664,
    "tp": 218.725,
    "trail_distance": 0.984,
    "trail_atr_mult": 2.0,
    "be_target_after_tp": 218.725,
    "max_target": 220.939,
    "tp_mode": "single_with_trail",
    "tp_hit": false,
    "trail_active": false,
    "extreme_price": 217.987,
    "tp1": 218.725,
    "tp2": 220.201,
    "tp3": 220.939,
    "ta_score": 90.3,
    "fa_score": 76.6,
    "fa_rate_diff": 2.75,
    "regime": "normal",
    "position_sizing": {
      "tradable": true,
      "units": 300,
      "margin_required_jpy": 2616.0,
      "risk_amount_jpy": 150.0,
      "estimated_loss_jpy": 97.0,
      "existing_margin_jpy": 0.0,
      "exposure_multiplier": 0.5,
      "note": "300GBP単位（証拠金約¥2616・想定損失¥97） ※相関リスクでロット50%に圧縮"
    },
    "units": 300,
    "current_price": 217.987,
    "current_stars": 5
  }
}